better_help/__init__.py
better_help/help.py
better_help/navigation.py
better_help/paginator.py
discord_better_help-1.3.0.dist-info/LICENSE
discord_better_help-1.3.0.dist-info/METADATA
discord_better_help-1.3.0.dist-info/WHEEL
discord_better_help-1.3.0.dist-info/top_level.txt
discord_better_help-1.3.0.dist-info/RECORD
