Metadata-Version: 2.1
Name: discord-better-help
Version: 1.3.0
Summary: An extension module for discord.py to make setting up a help command easier.
Home-page: https://pypi.python.org/pypi/discord-better-help
Author: Steven Shrewsbury
Author-email: 
License: MIT
Project-URL: Source, https://github.com/stshrewsburyDev/discord-better-help
Project-URL: Documentation, https://discord-better-help.readthedocs.io/en/latest/
Platform: UNKNOWN
Classifier: Programming Language :: Python
Classifier: Programming Language :: Python :: 3
Classifier: License :: OSI Approved :: MIT License
Classifier: Operating System :: OS Independent
Classifier: Topic :: Utilities
Classifier: Intended Audience :: Developers
Requires-Python: >=3.6
License-File: LICENSE
Requires-Dist: discord.py
